cimlab/__init__.py
cimlab/data_profile/__init__.py
cimlab/data_profile/cimext_2022/__init__.py
cimlab/data_profile/cimext_2022/gridappsd_cim_profile.py
cimlab/data_profile/rc4_2021/__init__.py
cimlab/data_profile/rc4_2021/gridappsd_cim_profile_rc4_2021.py
cimlab/loaders/__init__.py
cimlab/loaders/blazegraph/__init__.py
cimlab/loaders/blazegraph/blazegraph.py
cimlab/loaders/blazegraph/query_parsers.py
cimlab/loaders/gridappsd/__init__.py
cimlab/loaders/sparql/rc4_2021/__init__.py
cimlab/loaders/sparql/rc4_2021/ac_dc_terminal.py
cimlab/loaders/sparql/rc4_2021/ac_line_segment.py
cimlab/loaders/sparql/rc4_2021/ac_line_segment_phase.py
cimlab/loaders/sparql/rc4_2021/analog.py
cimlab/loaders/sparql/rc4_2021/asset.py
cimlab/loaders/sparql/rc4_2021/asset_info.py
cimlab/loaders/sparql/rc4_2021/base_voltage.py
cimlab/loaders/sparql/rc4_2021/battery_unit.py
cimlab/loaders/sparql/rc4_2021/breaker.py
cimlab/loaders/sparql/rc4_2021/cable_info.py
cimlab/loaders/sparql/rc4_2021/concentric_neutral_cable_info.py
cimlab/loaders/sparql/rc4_2021/disconnector.py
cimlab/loaders/sparql/rc4_2021/discrete.py
cimlab/loaders/sparql/rc4_2021/energy_consumer.py
cimlab/loaders/sparql/rc4_2021/energy_consumer_phase.py
cimlab/loaders/sparql/rc4_2021/fuse.py
cimlab/loaders/sparql/rc4_2021/get_class_type.py
cimlab/loaders/sparql/rc4_2021/linear_shunt_compensator.py
cimlab/loaders/sparql/rc4_2021/load_break_switch.py
cimlab/loaders/sparql/rc4_2021/no_load_test.py
cimlab/loaders/sparql/rc4_2021/overhead_wire_info.py
cimlab/loaders/sparql/rc4_2021/per_length_phase_impedance.py
cimlab/loaders/sparql/rc4_2021/per_length_sequence_impedance.py
cimlab/loaders/sparql/rc4_2021/phase_impedance_data.py
cimlab/loaders/sparql/rc4_2021/photovoltaic_unit.py
cimlab/loaders/sparql/rc4_2021/power_electronics_connection.py
cimlab/loaders/sparql/rc4_2021/power_electronics_connection_phase.py
cimlab/loaders/sparql/rc4_2021/power_transformer.py
cimlab/loaders/sparql/rc4_2021/power_transformer_end.py
gridappsd_cim_profile-0.11.20230209012720a0.dist-info/METADATA
gridappsd_cim_profile-0.11.20230209012720a0.dist-info/WHEEL
gridappsd_cim_profile-0.11.20230209012720a0.dist-info/RECORD
